carom/__init__.py
carom/__main__.py
carom/algo.py
carom/carom.py
carom/main.py
carom/tutorial.py
carom/dataset/__init__.py
carom/dataset/read_dataset.py
carom_sblab-0.1.2.data/scripts/cli
tests/__init__.py
tests/carom_test_install.py
carom_sblab-0.1.2.dist-info/LICENSE.txt
carom_sblab-0.1.2.dist-info/METADATA
carom_sblab-0.1.2.dist-info/WHEEL
carom_sblab-0.1.2.dist-info/entry_points.txt
carom_sblab-0.1.2.dist-info/top_level.txt
carom_sblab-0.1.2.dist-info/RECORD
